topsis_pkg/topsis.py
topsis_pkg-1.0.0.dist-info/LICENSE.txt
topsis_pkg-1.0.0.dist-info/METADATA
topsis_pkg-1.0.0.dist-info/WHEEL
topsis_pkg-1.0.0.dist-info/entry_points.txt
topsis_pkg-1.0.0.dist-info/top_level.txt
topsis_pkg-1.0.0.dist-info/RECORD
